{"generated":"2026-03-13T09:16:18.684Z","projects":[{"name":"UsageLedger","branch":"main","lastCommit":"2026-03-13T01:39:15-07:00","lastMsg":"feat: add repo standards and xcodegen project","dirty":3,"updatedToday":true,"ci":"none","vercel":"none","liveUrl":null,"github":"https://github.com/nulljosh/UsageLedger"},{"name":"applescripts","branch":"main","lastCommit":"2026-03-11T13:55:39-07:00","lastMsg":"fix: keep auto-dj logs out of git","dirty":0,"updatedToday":false,"ci":"none","vercel":"none","liveUrl":null,"github":"https://github.com/nulljosh/applescripts"},{"name":"arthur","branch":"main","lastCommit":"2026-03-13T01:59:11-07:00","lastMsg":"feat: replace fake chat with honest educational showcase","dirty":0,"updatedToday":true,"ci":"success","vercel":"none","liveUrl":"https://arthur.heyitsmejosh.com","github":"https://github.com/nulljosh/arthur"},{"name":"bank","branch":"main","lastCommit":"2026-03-09T09:01:37-07:00","lastMsg":"auto: daily sync 2026-03-09","dirty":0,"updatedToday":false,"ci":"none","vercel":"none","liveUrl":null,"github":"https://github.com/nulljosh/bank"},{"name":"bots","branch":"main","lastCommit":"2026-03-13T02:05:27-07:00","lastMsg":"refactor: clean up food project structure","dirty":10,"updatedToday":true,"ci":"success","vercel":"none","liveUrl":null,"github":"https://github.com/nulljosh/bots"},{"name":"brief","branch":"main","lastCommit":"2026-03-08T01:27:11-08:00","lastMsg":"chore: add simplify baseline and command docs","dirty":0,"updatedToday":false,"ci":"success","vercel":"none","liveUrl":null,"github":"https://github.com/nulljosh/brief"},{"name":"browser","branch":"main","lastCommit":"2026-03-09T09:01:39-07:00","lastMsg":"auto: daily sync 2026-03-09","dirty":0,"updatedToday":false,"ci":"none","vercel":"none","liveUrl":null,"github":"https://github.com/nulljosh/browser"},{"name":"chi","branch":"main","lastCommit":"2026-03-11T09:02:12-07:00","lastMsg":"auto: daily sync 2026-03-11","dirty":0,"updatedToday":false,"ci":"success","vercel":"success","liveUrl":"https://fs-one-gamma.vercel.app","github":"https://github.com/nulljosh/chi"},{"name":"dose","branch":"main","lastCommit":"2026-03-10T00:46:59-07:00","lastMsg":"style: update design tokens","dirty":0,"updatedToday":false,"ci":"success","vercel":"success","liveUrl":null,"github":"https://github.com/nulljosh/dose"},{"name":"dose-ios","branch":"main","lastCommit":"2026-03-13T01:27:50-07:00","lastMsg":"feat: add HealthView for biometric data display","dirty":0,"updatedToday":true,"ci":"none","vercel":"none","liveUrl":null,"github":"https://github.com/nulljosh/dose-ios"},{"name":"dotfiles","branch":"main","lastCommit":"2026-03-11T19:51:27-07:00","lastMsg":"Add Terminal-safe Starship prompt","dirty":0,"updatedToday":false,"ci":"none","vercel":"none","liveUrl":null,"github":"https://github.com/nulljosh/dotfiles"},{"name":"infra","branch":"main","lastCommit":"2026-03-08T01:27:17-08:00","lastMsg":"chore: add simplify baseline and command docs","dirty":0,"updatedToday":false,"ci":"none","vercel":"none","liveUrl":null,"github":"https://github.com/nulljosh/infra"},{"name":"jot","branch":"main","lastCommit":"2026-03-11T19:44:15-07:00","lastMsg":"Add jot checkpoints and closure groundwork","dirty":0,"updatedToday":false,"ci":"none","vercel":"none","liveUrl":null,"github":"https://github.com/nulljosh/jot"},{"name":"journal","branch":"main","lastCommit":"2026-03-13T02:15:45-07:00","lastMsg":"fix: remove AI-speak from Mar 2 entry","dirty":0,"updatedToday":true,"ci":"success","vercel":"none","liveUrl":"https://heyitsmejosh.com/journal","github":"https://github.com/nulljosh/journal"},{"name":"lingo","branch":"main","lastCommit":"2026-03-12T09:02:20-07:00","lastMsg":"auto: daily sync 2026-03-12","dirty":0,"updatedToday":false,"ci":"none","vercel":"success","liveUrl":"https://lingo.heyitsmejosh.com","github":"https://github.com/nulljosh/lingo"},{"name":"notes","branch":"main","lastCommit":"2026-03-13T01:56:44-07:00","lastMsg":"docs: refresh master.md task list to current state","dirty":0,"updatedToday":true,"ci":"success","vercel":"none","liveUrl":null,"github":"https://github.com/nulljosh/notes"},{"name":"nulljosh.github.io","branch":"main","lastCommit":"2026-03-11T19:34:15-07:00","lastMsg":"Simplify skills section copy","dirty":0,"updatedToday":false,"ci":"success","vercel":"none","liveUrl":"https://heyitsmejosh.com","github":"https://github.com/nulljosh/nulljosh.github.io"},{"name":"opticon","branch":"main","lastCommit":"2026-03-13T02:04:43-07:00","lastMsg":"feat: multi-source news, savings forecast, auto-location","dirty":0,"updatedToday":true,"ci":"success","vercel":"success","liveUrl":"https://opticon.heyitsmejosh.com","github":"https://github.com/nulljosh/opticon"},{"name":"opticon-ios","branch":"main","lastCommit":"2026-03-13T02:04:43-07:00","lastMsg":"feat: iOS polish pass -- avatars, auto-location, iconography, empty states","dirty":0,"updatedToday":true,"ci":"none","vercel":"none","liveUrl":null,"github":"https://github.com/nulljosh/opticon-ios"},{"name":"opticon-macos","branch":"main","lastCommit":"2026-03-12T09:02:23-07:00","lastMsg":"auto: daily sync 2026-03-12","dirty":0,"updatedToday":false,"ci":"none","vercel":"none","liveUrl":null,"github":"https://github.com/nulljosh/opticon-macos"},{"name":"pdf","branch":"main","lastCommit":"2026-03-09T19:27:35-07:00","lastMsg":"fix: dark mode hover shadow, scope pill hover to links, remove dead rule","dirty":0,"updatedToday":false,"ci":"success","vercel":"none","liveUrl":null,"github":"https://github.com/nulljosh/pdf"},{"name":"piper","branch":"main","lastCommit":"2026-03-08T20:57:46-07:00","lastMsg":"feat: wire ArthurLLM to Flask HTTP endpoint","dirty":0,"updatedToday":false,"ci":"none","vercel":"none","liveUrl":null,"github":"https://github.com/nulljosh/piper"},{"name":"rabbit","branch":"main","lastCommit":"2026-03-08T22:04:20-07:00","lastMsg":"docs: sync badge to v2.1.0","dirty":0,"updatedToday":false,"ci":"none","vercel":"success","liveUrl":"https://rabbit-lyart.vercel.app","github":"https://github.com/nulljosh/rabbit"},{"name":"spark","branch":"main","lastCommit":"2026-03-09T09:01:42-07:00","lastMsg":"auto: daily sync 2026-03-09","dirty":0,"updatedToday":false,"ci":"success","vercel":"success","liveUrl":"https://spark.heyitsmejosh.com","github":"https://github.com/nulljosh/spark"},{"name":"spark-ios","branch":"main","lastCommit":"2026-03-11T18:48:13-07:00","lastMsg":"Add biometric sign-in","dirty":0,"updatedToday":false,"ci":"none","vercel":"none","liveUrl":null,"github":"https://github.com/nulljosh/spark-ios"},{"name":"starbot","branch":"main","lastCommit":"2026-03-08T21:14:07-07:00","lastMsg":"feat: starbot CLI with deprecation-aware API stubs","dirty":0,"updatedToday":false,"ci":"none","vercel":"none","liveUrl":null,"github":"https://github.com/nulljosh/starbot"},{"name":"systems","branch":"main","lastCommit":"2026-03-08T01:27:29-08:00","lastMsg":"chore: add simplify baseline and command docs","dirty":0,"updatedToday":false,"ci":"none","vercel":"none","liveUrl":null,"github":"https://github.com/nulljosh/systems"},{"name":"tally","branch":"main","lastCommit":"2026-03-13T01:51:44-07:00","lastMsg":"fix: remove all gradient backgrounds per design rules","dirty":0,"updatedToday":true,"ci":"success","vercel":"success","liveUrl":"https://tally.heyitsmejosh.com","github":"https://github.com/nulljosh/tally"},{"name":"tally-ios","branch":"main","lastCommit":"2026-03-13T02:09:45-07:00","lastMsg":"feat: auto sync, CRA view, settings, DTC polish, forms cleanup","dirty":0,"updatedToday":true,"ci":"none","vercel":"none","liveUrl":null,"github":"https://github.com/nulljosh/tally-ios"},{"name":"vibe","branch":"main","lastCommit":"2026-03-12T09:02:27-07:00","lastMsg":"auto: daily sync 2026-03-12","dirty":0,"updatedToday":false,"ci":"success","vercel":"none","liveUrl":null,"github":"https://github.com/nulljosh/vibe"},{"name":"zillow-clone","branch":"main","lastCommit":"2026-03-09T09:01:46-07:00","lastMsg":"auto: daily sync 2026-03-09","dirty":0,"updatedToday":false,"ci":"none","vercel":"none","liveUrl":null,"github":"https://github.com/nulljosh/zillow-clone"}],"stats":{"totalRepos":31,"updatedToday":10,"date":"2026-03-13"}}